{
 "custom_fields": [
  {
   "_assign": null,
   "_comments": null,
   "_liked_by": null,
   "_user_tags": null,
   "allow_in_quick_entry": 0,
   "allow_on_submit": 0,
   "bold": 0,
   "collapsible": 0,
   "collapsible_depends_on": null,
   "columns": 0,
   "creation": "2019-12-02 11:00:03.432994",
   "default": null,
   "depends_on": null,
   "description": null,
   "docstatus": 0,
   "dt": "Contact",
   "fetch_from": null,
   "fetch_if_empty": 0,
   "fieldname": "is_billing_contact",
   "fieldtype": "Check",
   "hidden": 0,
   "hide_border": 0,
   "hide_days": 0,
   "hide_seconds": 0,
   "idx": 33,
   "ignore_user_permissions": 0,
   "ignore_xss_filter": 0,
   "in_global_search": 0,
   "in_list_view": 0,
   "in_preview": 0,
   "in_standard_filter": 0,
   "insert_after": "is_primary_contact",
   "is_system_generated": 0,
   "is_virtual": 0,
   "label": "Is Billing Contact",
   "length": 0,
   "mandatory_depends_on": null,
   "modified": "2019-12-02 11:00:03.432994",
   "modified_by": "Administrator",
   "module": null,
   "name": "Contact-is_billing_contact",
   "no_copy": 0,
   "non_negative": 0,
   "options": null,
   "owner": "Administrator",
   "permlevel": 0,
   "precision": "",
   "print_hide": 0,
   "print_hide_if_no_value": 0,
   "print_width": null,
   "read_only": 0,
   "read_only_depends_on": null,
   "report_hide": 0,
   "reqd": 0,
   "search_index": 0,
   "sort_options": 0,
   "translatable": 0,
   "unique": 0,
   "width": null
  },
  {
   "_assign": null,
   "_comments": null,
   "_liked_by": null,
   "_user_tags": null,
   "allow_in_quick_entry": 0,
   "allow_on_submit": 0,
   "bold": 0,
   "collapsible": 0,
   "collapsible_depends_on": null,
   "columns": 0,
   "creation": "2023-10-16 15:06:51.119756",
   "default": null,
   "depends_on": "",
   "description": null,
   "docstatus": 0,
   "dt": "Contact",
   "fetch_from": null,
   "fetch_if_empty": 0,
   "fieldname": "custom_research_portal_access",
   "fieldtype": "Section Break",
   "hidden": 0,
   "hide_border": 0,
   "hide_days": 0,
   "hide_seconds": 0,
   "idx": 18,
   "ignore_user_permissions": 0,
   "ignore_xss_filter": 0,
   "in_global_search": 0,
   "in_list_view": 0,
   "in_preview": 0,
   "in_standard_filter": 0,
   "insert_after": "image",
   "is_system_generated": 0,
   "is_virtual": 0,
   "label": "Research Portal Access",
   "length": 0,
   "mandatory_depends_on": null,
   "modified": "2023-10-16 15:06:51.119756",
   "modified_by": "Administrator",
   "module": null,
   "name": "Contact-custom_research_portal_access",
   "no_copy": 0,
   "non_negative": 0,
   "options": null,
   "owner": "Administrator",
   "permlevel": 0,
   "precision": "",
   "print_hide": 0,
   "print_hide_if_no_value": 0,
   "print_width": null,
   "read_only": 0,
   "read_only_depends_on": null,
   "report_hide": 0,
   "reqd": 0,
   "search_index": 0,
   "sort_options": 0,
   "translatable": 0,
   "unique": 0,
   "width": null
  },
  {
   "_assign": null,
   "_comments": null,
   "_liked_by": null,
   "_user_tags": null,
   "allow_in_quick_entry": 0,
   "allow_on_submit": 0,
   "bold": 0,
   "collapsible": 0,
   "collapsible_depends_on": null,
   "columns": 0,
   "creation": "2023-10-16 15:06:51.318829",
   "default": null,
   "depends_on": null,
   "description": "Leave empty if no access restriction",
   "docstatus": 0,
   "dt": "Contact",
   "fetch_from": null,
   "fetch_if_empty": 0,
   "fieldname": "custom_access_valid_till",
   "fieldtype": "Date",
   "hidden": 0,
   "hide_border": 0,
   "hide_days": 0,
   "hide_seconds": 0,
   "idx": 21,
   "ignore_user_permissions": 0,
   "ignore_xss_filter": 0,
   "in_global_search": 0,
   "in_list_view": 0,
   "in_preview": 0,
   "in_standard_filter": 0,
   "insert_after": "custom_column_break_jcts8",
   "is_system_generated": 0,
   "is_virtual": 0,
   "label": "Access Valid Till",
   "length": 0,
   "mandatory_depends_on": null,
   "modified": "2023-10-16 15:06:51.318829",
   "modified_by": "Administrator",
   "module": null,
   "name": "Contact-custom_access_valid_till",
   "no_copy": 0,
   "non_negative": 0,
   "options": null,
   "owner": "Administrator",
   "permlevel": 0,
   "precision": "",
   "print_hide": 0,
   "print_hide_if_no_value": 0,
   "print_width": null,
   "read_only": 0,
   "read_only_depends_on": null,
   "report_hide": 0,
   "reqd": 0,
   "search_index": 0,
   "sort_options": 0,
   "translatable": 0,
   "unique": 0,
   "width": null
  },
  {
   "_assign": null,
   "_comments": null,
   "_liked_by": null,
   "_user_tags": null,
   "allow_in_quick_entry": 0,
   "allow_on_submit": 0,
   "bold": 0,
   "collapsible": 0,
   "collapsible_depends_on": null,
   "columns": 0,
   "creation": "2023-11-07 11:57:35.572343",
   "default": null,
   "depends_on": null,
   "description": null,
   "docstatus": 0,
   "dt": "Contact",
   "fetch_from": null,
   "fetch_if_empty": 0,
   "fieldname": "custom_has_portal_access",
   "fieldtype": "Check",
   "hidden": 0,
   "hide_border": 0,
   "hide_days": 0,
   "hide_seconds": 0,
   "idx": 19,
   "ignore_user_permissions": 0,
   "ignore_xss_filter": 0,
   "in_global_search": 0,
   "in_list_view": 0,
   "in_preview": 0,
   "in_standard_filter": 0,
   "insert_after": "custom_research_portal_access",
   "is_system_generated": 0,
   "is_virtual": 0,
   "label": "Has Portal Access",
   "length": 0,
   "mandatory_depends_on": null,
   "modified": "2023-11-07 11:57:35.572343",
   "modified_by": "Administrator",
   "module": null,
   "name": "Contact-custom_has_portal_access",
   "no_copy": 0,
   "non_negative": 0,
   "options": null,
   "owner": "Administrator",
   "permlevel": 0,
   "precision": "",
   "print_hide": 0,
   "print_hide_if_no_value": 0,
   "print_width": null,
   "read_only": 0,
   "read_only_depends_on": null,
   "report_hide": 0,
   "reqd": 0,
   "search_index": 0,
   "sort_options": 0,
   "translatable": 0,
   "unique": 0,
   "width": null
  },
  {
   "_assign": null,
   "_comments": null,
   "_liked_by": null,
   "_user_tags": null,
   "allow_in_quick_entry": 0,
   "allow_on_submit": 0,
   "bold": 0,
   "collapsible": 0,
   "collapsible_depends_on": null,
   "columns": 0,
   "creation": "2023-11-07 11:58:21.057114",
   "default": null,
   "depends_on": null,
   "description": null,
   "docstatus": 0,
   "dt": "Contact",
   "fetch_from": null,
   "fetch_if_empty": 0,
   "fieldname": "custom_column_break_jcts8",
   "fieldtype": "Column Break",
   "hidden": 0,
   "hide_border": 0,
   "hide_days": 0,
   "hide_seconds": 0,
   "idx": 20,
   "ignore_user_permissions": 0,
   "ignore_xss_filter": 0,
   "in_global_search": 0,
   "in_list_view": 0,
   "in_preview": 0,
   "in_standard_filter": 0,
   "insert_after": "custom_has_portal_access",
   "is_system_generated": 0,
   "is_virtual": 0,
   "label": null,
   "length": 0,
   "mandatory_depends_on": null,
   "modified": "2023-11-07 11:58:21.057114",
   "modified_by": "Administrator",
   "module": null,
   "name": "Contact-custom_column_break_jcts8",
   "no_copy": 0,
   "non_negative": 0,
   "options": null,
   "owner": "Administrator",
   "permlevel": 0,
   "precision": "",
   "print_hide": 0,
   "print_hide_if_no_value": 0,
   "print_width": null,
   "read_only": 0,
   "read_only_depends_on": null,
   "report_hide": 0,
   "reqd": 0,
   "search_index": 0,
   "sort_options": 0,
   "translatable": 0,
   "unique": 0,
   "width": null
  }
 ],
 "custom_perms": [
  {
   "_assign": null,
   "_comments": null,
   "_liked_by": null,
   "_user_tags": null,
   "amend": 0,
   "cancel": 0,
   "create": 1,
   "creation": "2023-01-04 00:02:12.212770",
   "delete": 0,
   "docstatus": 0,
   "email": 1,
   "export": 0,
   "idx": 5,
   "if_owner": 0,
   "import": 0,
   "modified": "2023-01-04 00:02:12.212770",
   "modified_by": "Administrator",
   "name": "2bab412281",
   "owner": "Administrator",
   "parent": "Contact",
   "permlevel": 0,
   "print": 1,
   "read": 1,
   "report": 1,
   "role": "Purchase Manager",
   "select": 0,
   "set_user_permissions": 0,
   "share": 1,
   "submit": 0,
   "write": 1
  },
  {
   "_assign": null,
   "_comments": null,
   "_liked_by": null,
   "_user_tags": null,
   "amend": 0,
   "cancel": 0,
   "create": 1,
   "creation": "2023-01-04 00:02:12.304236",
   "delete": 0,
   "docstatus": 0,
   "email": 1,
   "export": 0,
   "idx": 9,
   "if_owner": 0,
   "import": 0,
   "modified": "2023-01-04 00:02:12.304236",
   "modified_by": "Administrator",
   "name": "21eacf0ec7",
   "owner": "Administrator",
   "parent": "Contact",
   "permlevel": 0,
   "print": 1,
   "read": 1,
   "report": 1,
   "role": "Purchase User",
   "select": 0,
   "set_user_permissions": 0,
   "share": 1,
   "submit": 0,
   "write": 1
  },
  {
   "_assign": null,
   "_comments": null,
   "_liked_by": null,
   "_user_tags": null,
   "amend": 0,
   "cancel": 0,
   "create": 1,
   "creation": "2023-01-04 00:02:12.365529",
   "delete": 1,
   "docstatus": 0,
   "email": 1,
   "export": 1,
   "idx": 1,
   "if_owner": 0,
   "import": 1,
   "modified": "2023-01-04 00:02:12.365529",
   "modified_by": "Administrator",
   "name": "9807d21238",
   "owner": "Administrator",
   "parent": "Contact",
   "permlevel": 0,
   "print": 1,
   "read": 1,
   "report": 1,
   "role": "System Manager",
   "select": 0,
   "set_user_permissions": 1,
   "share": 1,
   "submit": 0,
   "write": 1
  },
  {
   "_assign": null,
   "_comments": null,
   "_liked_by": null,
   "_user_tags": null,
   "amend": 0,
   "cancel": 0,
   "create": 0,
   "creation": "2023-01-04 00:02:12.423181",
   "delete": 0,
   "docstatus": 0,
   "email": 0,
   "export": 0,
   "idx": 12,
   "if_owner": 0,
   "import": 0,
   "modified": "2023-01-04 00:02:12.423181",
   "modified_by": "Administrator",
   "name": "f0fbc8cb70",
   "owner": "Administrator",
   "parent": "Contact",
   "permlevel": 1,
   "print": 0,
   "read": 1,
   "report": 1,
   "role": "All",
   "select": 0,
   "set_user_permissions": 0,
   "share": 0,
   "submit": 0,
   "write": 0
  },
  {
   "_assign": null,
   "_comments": null,
   "_liked_by": null,
   "_user_tags": null,
   "amend": 0,
   "cancel": 0,
   "create": 1,
   "creation": "2023-01-04 00:02:12.477989",
   "delete": 1,
   "docstatus": 0,
   "email": 1,
   "export": 0,
   "idx": 2,
   "if_owner": 0,
   "import": 0,
   "modified": "2023-01-04 00:02:12.477989",
   "modified_by": "Administrator",
   "name": "437bf83449",
   "owner": "Administrator",
   "parent": "Contact",
   "permlevel": 0,
   "print": 1,
   "read": 1,
   "report": 1,
   "role": "Sales Master Manager",
   "select": 0,
   "set_user_permissions": 0,
   "share": 1,
   "submit": 0,
   "write": 1
  },
  {
   "_assign": null,
   "_comments": null,
   "_liked_by": null,
   "_user_tags": null,
   "amend": 0,
   "cancel": 0,
   "create": 1,
   "creation": "2023-01-04 00:02:12.548667",
   "delete": 1,
   "docstatus": 0,
   "email": 1,
   "export": 0,
   "idx": 3,
   "if_owner": 0,
   "import": 0,
   "modified": "2023-01-04 00:02:12.548667",
   "modified_by": "Administrator",
   "name": "80a34b1e11",
   "owner": "Administrator",
   "parent": "Contact",
   "permlevel": 0,
   "print": 1,
   "read": 1,
   "report": 1,
   "role": "Purchase Master Manager",
   "select": 0,
   "set_user_permissions": 0,
   "share": 1,
   "submit": 0,
   "write": 1
  },
  {
   "_assign": null,
   "_comments": null,
   "_liked_by": null,
   "_user_tags": null,
   "amend": 0,
   "cancel": 0,
   "create": 1,
   "creation": "2023-01-04 00:02:12.603880",
   "delete": 0,
   "docstatus": 0,
   "email": 1,
   "export": 0,
   "idx": 7,
   "if_owner": 0,
   "import": 0,
   "modified": "2023-01-04 00:02:12.603880",
   "modified_by": "Administrator",
   "name": "9d1c4ff48f",
   "owner": "Administrator",
   "parent": "Contact",
   "permlevel": 0,
   "print": 1,
   "read": 1,
   "report": 1,
   "role": "Accounts Manager",
   "select": 0,
   "set_user_permissions": 0,
   "share": 1,
   "submit": 0,
   "write": 1
  },
  {
   "_assign": null,
   "_comments": null,
   "_liked_by": null,
   "_user_tags": null,
   "amend": 0,
   "cancel": 0,
   "create": 1,
   "creation": "2023-01-04 00:02:12.659508",
   "delete": 0,
   "docstatus": 0,
   "email": 1,
   "export": 0,
   "idx": 8,
   "if_owner": 0,
   "import": 0,
   "modified": "2023-01-04 00:02:12.659508",
   "modified_by": "Administrator",
   "name": "8faf4ad658",
   "owner": "Administrator",
   "parent": "Contact",
   "permlevel": 0,
   "print": 1,
   "read": 1,
   "report": 1,
   "role": "Sales User",
   "select": 0,
   "set_user_permissions": 0,
   "share": 1,
   "submit": 0,
   "write": 1
  },
  {
   "_assign": null,
   "_comments": null,
   "_liked_by": null,
   "_user_tags": null,
   "amend": 0,
   "cancel": 0,
   "create": 1,
   "creation": "2023-01-04 00:02:12.717891",
   "delete": 0,
   "docstatus": 0,
   "email": 1,
   "export": 0,
   "idx": 10,
   "if_owner": 0,
   "import": 0,
   "modified": "2023-01-04 00:02:12.717891",
   "modified_by": "Administrator",
   "name": "aa4fcdb6a1",
   "owner": "Administrator",
   "parent": "Contact",
   "permlevel": 0,
   "print": 1,
   "read": 1,
   "report": 1,
   "role": "Maintenance User",
   "select": 0,
   "set_user_permissions": 0,
   "share": 1,
   "submit": 0,
   "write": 1
  },
  {
   "_assign": null,
   "_comments": null,
   "_liked_by": null,
   "_user_tags": null,
   "amend": 0,
   "cancel": 0,
   "create": 1,
   "creation": "2023-01-04 00:02:12.769059",
   "delete": 0,
   "docstatus": 0,
   "email": 1,
   "export": 0,
   "idx": 4,
   "if_owner": 0,
   "import": 0,
   "modified": "2023-01-04 00:02:12.769059",
   "modified_by": "Administrator",
   "name": "71bdde0bdf",
   "owner": "Administrator",
   "parent": "Contact",
   "permlevel": 0,
   "print": 1,
   "read": 1,
   "report": 1,
   "role": "Sales Manager",
   "select": 0,
   "set_user_permissions": 0,
   "share": 1,
   "submit": 0,
   "write": 1
  },
  {
   "_assign": null,
   "_comments": null,
   "_liked_by": null,
   "_user_tags": null,
   "amend": 0,
   "cancel": 0,
   "create": 1,
   "creation": "2023-01-04 00:02:12.836745",
   "delete": 0,
   "docstatus": 0,
   "email": 1,
   "export": 0,
   "idx": 11,
   "if_owner": 0,
   "import": 0,
   "modified": "2023-01-04 00:02:12.836745",
   "modified_by": "Administrator",
   "name": "596f503655",
   "owner": "Administrator",
   "parent": "Contact",
   "permlevel": 0,
   "print": 1,
   "read": 1,
   "report": 1,
   "role": "Accounts User",
   "select": 0,
   "set_user_permissions": 0,
   "share": 1,
   "submit": 0,
   "write": 1
  },
  {
   "_assign": null,
   "_comments": null,
   "_liked_by": null,
   "_user_tags": null,
   "amend": 0,
   "cancel": 0,
   "create": 1,
   "creation": "2023-01-04 00:02:12.898975",
   "delete": 0,
   "docstatus": 0,
   "email": 1,
   "export": 0,
   "idx": 6,
   "if_owner": 0,
   "import": 0,
   "modified": "2023-01-04 00:02:12.898975",
   "modified_by": "Administrator",
   "name": "469790971d",
   "owner": "Administrator",
   "parent": "Contact",
   "permlevel": 0,
   "print": 1,
   "read": 1,
   "report": 1,
   "role": "Maintenance Manager",
   "select": 0,
   "set_user_permissions": 0,
   "share": 1,
   "submit": 0,
   "write": 1
  },
  {
   "_assign": null,
   "_comments": null,
   "_liked_by": null,
   "_user_tags": null,
   "amend": 0,
   "cancel": 0,
   "create": 0,
   "creation": "2023-01-04 00:02:12.958287",
   "delete": 0,
   "docstatus": 0,
   "email": 0,
   "export": 1,
   "idx": 0,
   "if_owner": 0,
   "import": 0,
   "modified": "2023-01-04 00:02:12.958287",
   "modified_by": "Administrator",
   "name": "a4fc219020",
   "owner": "Administrator",
   "parent": "Contact",
   "permlevel": 0,
   "print": 0,
   "read": 1,
   "report": 0,
   "role": "Client Vote User",
   "select": 1,
   "set_user_permissions": 0,
   "share": 0,
   "submit": 0,
   "write": 0
  },
  {
   "_assign": null,
   "_comments": null,
   "_liked_by": null,
   "_user_tags": null,
   "amend": 0,
   "cancel": 0,
   "create": 1,
   "creation": "2023-01-04 00:02:28.880819",
   "delete": 0,
   "docstatus": 0,
   "email": 0,
   "export": 1,
   "idx": 0,
   "if_owner": 0,
   "import": 0,
   "modified": "2023-01-04 00:02:28.880819",
   "modified_by": "Administrator",
   "name": "a3c8091af1",
   "owner": "Administrator",
   "parent": "Contact",
   "permlevel": 0,
   "print": 0,
   "read": 1,
   "report": 0,
   "role": "Client Vote Manager",
   "select": 1,
   "set_user_permissions": 0,
   "share": 0,
   "submit": 0,
   "write": 1
  }
 ],
 "doctype": "Contact",
 "links": [],
 "property_setters": [
  {
   "_assign": null,
   "_comments": null,
   "_liked_by": null,
   "_user_tags": null,
   "creation": "2023-12-01 14:30:16.844667",
   "default_value": null,
   "doc_type": "Contact",
   "docstatus": 0,
   "doctype_or_field": "DocType",
   "field_name": null,
   "idx": 0,
   "is_system_generated": 0,
   "modified": "2023-12-01 14:30:16.844667",
   "modified_by": "Administrator",
   "module": null,
   "name": "Contact-main-field_order",
   "owner": "Administrator",
   "property": "field_order",
   "property_type": "Data",
   "row_name": null,
   "value": "[\"contact_section\", \"first_name\", \"middle_name\", \"last_name\", \"email_id\", \"user\", \"address\", \"sync_with_google_contacts\", \"cb00\", \"status\", \"salutation\", \"designation\", \"gender\", \"phone\", \"mobile_no\", \"company_name\", \"image\", \"custom_research_portal_access\", \"custom_has_portal_access\", \"custom_column_break_jcts8\", \"custom_access_valid_till\", \"sb_00\", \"google_contacts\", \"google_contacts_id\", \"cb_00\", \"pulled_from_google_contacts\", \"sb_01\", \"email_ids\", \"phone_nos\", \"contact_details\", \"links\", \"is_primary_contact\", \"is_billing_contact\", \"more_info\", \"department\", \"unsubscribed\"]"
  },
  {
   "_assign": null,
   "_comments": null,
   "_liked_by": null,
   "_user_tags": null,
   "creation": "2023-10-16 15:09:16.323266",
   "default_value": null,
   "doc_type": "Contact",
   "docstatus": 0,
   "doctype_or_field": "DocField",
   "field_name": "email_id",
   "idx": 0,
   "is_system_generated": 0,
   "modified": "2023-10-16 15:09:16.323266",
   "modified_by": "Administrator",
   "module": null,
   "name": "Contact-email_id-mandatory_depends_on",
   "owner": "Administrator",
   "property": "mandatory_depends_on",
   "property_type": "Data",
   "row_name": null,
   "value": "eval: doc.custom_sync_with_research_portal"
  }
 ],
 "sync_on_migrate": 1
}